auto_video_cut/__init__.py
auto_video_cut/auto_video_cut.py
auto_video_cut-0.0.2.dist-info/LICENSE
auto_video_cut-0.0.2.dist-info/METADATA
auto_video_cut-0.0.2.dist-info/WHEEL
auto_video_cut-0.0.2.dist-info/top_level.txt
auto_video_cut-0.0.2.dist-info/RECORD
