Metadata-Version: 2.1
Name: auto-video-cut
Version: 0.0.2
Summary: Cut unnecessary parts of a video
Home-page: https://github.com/ybalcanci/auto_video_cut
Author: Yasin Balcancı
Author-email: ybalcanci@gmail.com
License: UNKNOWN
Platform: UNKNOWN
Classifier: Programming Language :: Python :: 3
Classifier: Operating System :: OS Independent
Requires-Python: >=3.9
